opendalfs/__init__.py
opendalfs/decorator.py
opendalfs/file.py
opendalfs/fs.py
opendalfs-0.0.1.dist-info/licenses/LICENSE
opendalfs-0.0.1.dist-info/METADATA
opendalfs-0.0.1.dist-info/WHEEL
opendalfs-0.0.1.dist-info/top_level.txt
opendalfs-0.0.1.dist-info/RECORD
