Metadata-Version: 2.4
Name: opendalfs
Version: 0.0.1
Classifier: Development Status :: 4 - Beta
Classifier: Intended Audience :: Developers
Classifier: License :: OSI Approved :: Apache Software License
Classifier: Operating System :: OS Independent
Classifier: Programming Language :: Python :: 3.11
Classifier: Programming Language :: Python :: 3.12
Requires-Python: >=3.12
License-File: LICENSE
Requires-Dist: fsspec
Requires-Dist: opendal
Provides-Extra: dev
Requires-Dist: ruff; extra == "dev"
Provides-Extra: test
Requires-Dist: pytest; extra == "test"
Requires-Dist: pytest-asyncio; extra == "test"
Requires-Dist: pytest-cov; extra == "test"
Requires-Dist: s3fs; extra == "test"
Requires-Dist: boto3; extra == "test"
Provides-Extra: all
Requires-Dist: opendalfs[dev,test]; extra == "all"
Dynamic: license-file
